rnd_logger/__init__.py
rnd_logger/config.py
rnd_logger/incident_severity.py
rnd_logger/rnd_logger.py
rnd_logger-1.4.5.dist-info/METADATA
rnd_logger-1.4.5.dist-info/WHEEL
rnd_logger-1.4.5.dist-info/RECORD
