Metadata-Version: 2.1
Name: rnd-logger
Version: 1.4.5
Summary: Made Tech R&D Logger
Author: Made Tech R&D Engineering
Author-email: rnd-engineering@madetech.com
Requires-Python: >=3.11,<4.0
Classifier: Programming Language :: Python :: 3
Classifier: Programming Language :: Python :: 3.11
Classifier: Programming Language :: Python :: 3.12
Requires-Dist: python-json-logger (>=2.0.7,<3.0.0)
Requires-Dist: sentry-sdk (>=1.32,<3.0)
